{
  "phase": "第一阶段",
  "trade_date": "20260226",
  "total_score": 0.45999999999999996,
  "expectation_level": "低于预期",
  "indicator_results": [
    {
      "code": "S1-01",
      "name": "资金回流连续性",
      "value": 0.25,
      "weight": 0.22,
      "unit": "pct",
      "direction": "higher_better",
      "expectation": "低于预期",
      "trade_date": "20260226"
    },
    {
      "code": "S1-02",
      "name": "ETF份额变化",
      "value": -0.10737807305478624,
      "weight": 0.18,
      "unit": "pct",
      "direction": "higher_better",
      "expectation": "低于预期",
      "trade_date": "20260226"
    },
    {
      "code": "S1-03",
      "name": "ETF相对强度",
      "value": 0.0015176319116336247,
      "weight": 0.2,
      "unit": "pct",
      "direction": "higher_better",
      "expectation": "符合预期",
      "trade_date": "20260226"
    },
    {
      "code": "S1-04",
      "name": "成交放大持续性",
      "value": 0.6764443522615123,
      "weight": 0.14,
      "unit": "ratio",
      "direction": "higher_better",
      "expectation": "低于预期",
      "trade_date": "20260226"
    },
    {
      "code": "S1-05",
      "name": "板块广度修复",
      "value": 0.26666666666666666,
      "weight": 0.14,
      "unit": "pct",
      "direction": "higher_better",
      "expectation": "低于预期",
      "trade_date": "20260226"
    },
    {
      "code": "S1-06",
      "name": "龙头先行强度",
      "value": -0.016270064893534622,
      "weight": 0.12,
      "unit": "pct",
      "direction": "higher_better",
      "expectation": "低于预期",
      "trade_date": "20260226"
    }
  ],
  "summary": "综合得分 0.46，整体表现低于预期。6项指标中：超预期0项，符合预期1项，低于预期5项。主要特征：资金回流连续性需关注、ETF份额变化需关注、成交放大持续性需关注。"
}